AUTHORS
ChangeLog
README.rst
requirements.txt
setup.cfg
setup.py
exhibitor2dns/__init__.py
exhibitor2dns/main.py
exhibitor2dns.egg-info/PKG-INFO
exhibitor2dns.egg-info/SOURCES.txt
exhibitor2dns.egg-info/dependency_links.txt
exhibitor2dns.egg-info/entry_points.txt
exhibitor2dns.egg-info/not-zip-safe
exhibitor2dns.egg-info/requires.txt
exhibitor2dns.egg-info/top_level.txt