Metadata-Version: 1.0
Name: exhibitor2dns
Version: 0.1.2
Summary: Dynamically sync Route53 DNS entries for Zookeeper servers in an Exhibitor cluster
Home-page: http://github.com/benley/exhibitor2dns
Author: Benjamin Staffin
Author-email: benley@gmail.com
License: Apache-2
Platform: UNKNOWN
